{
  "global": {
    "size": {
      "value": "size",
      "type": "sizing"
    },
    "bg-primary-light": {
      "value": "#F7F8FB",
      "type": "color"
    },
    "bg-primary-dark": {
      "value": "#030712",
      "type": "color"
    },
    "primary": {
      "value": "#0E45B7",
      "type": "color"
    }
  },
  "global/global": {
    "primary": {
      "value": "#ffffff",
      "type": "color"
    },
    "size": {
      "value": "0rem",
      "type": "dimension"
    }
  },
  "$themes": [],
  "$metadata": {
    "tokenSetOrder": [
      "global",
      "global/global"
    ]
  }
}